kong/__init__.py
kong/common/__init__.py
kong/common/app_logger.py
kong/common/env.py
kong/common/error.py
kong/common/exceptions.py
kong/common/guard.py
kong/common/json.py
kong/common/telemetry.py
kong/common/timed.py
kong/proto/__init__.py
kong/proto/healthcheck.proto
kong/proto/healthcheck_pb2.py
kong/proto/healthcheck_pb2_grpc.py
kong/proto/service.proto
kong/proto/service_pb2.py
kong/proto/service_pb2_grpc.py
kong/sdk/__init__.py
kong/sdk/app.py
kong/sdk/config.json
kong/sdk/config.py
kong/sdk/conftest.py
kong/sdk/container.py
kong/sdk/grpc_binding.py
kong/sdk/health_check.py
kong/sdk/health_check_call.py
kong/sdk/kong_function.py
kong/sdk/kong_function_instance.py
kong/sdk/use_state.py
kong/session/__init__.py
kong/session/job_session_context.py
kong/session/session_context.py
kong_sdk-0.0.42.dist-info/METADATA
kong_sdk-0.0.42.dist-info/WHEEL
kong_sdk-0.0.42.dist-info/entry_points.txt
kong_sdk-0.0.42.dist-info/RECORD
