Metadata-Version: 2.4
Name: kong-sdk
Version: 0.0.42
Summary: Kong Python SDK
Requires-Python: >=3.9
Classifier: Programming Language :: Python :: 3
Classifier: Programming Language :: Python :: 3.9
Classifier: Programming Language :: Python :: 3.10
Classifier: Programming Language :: Python :: 3.11
Classifier: Programming Language :: Python :: 3.12
Classifier: Programming Language :: Python :: 3.13
Classifier: Programming Language :: Python :: 3.14
Requires-Dist: annotated-types (==0.7.0) ; python_version >= "3.9"
Requires-Dist: certifi (==2025.11.12) ; python_version >= "3.9"
Requires-Dist: charset-normalizer (==3.4.4) ; python_version >= "3.9"
Requires-Dist: dependency-injector (==4.48.1) ; python_version >= "3.9"
Requires-Dist: googleapis-common-protos (==1.72.0) ; python_version >= "3.9"
Requires-Dist: grpcio (==1.76.0) ; python_version >= "3.9"
Requires-Dist: grpcio-health-checking (==1.75.0) ; python_version >= "3.9"
Requires-Dist: grpcio-reflection (==1.75.0) ; python_version >= "3.9"
Requires-Dist: grpcio-tools (==1.75.0) ; python_version >= "3.9"
Requires-Dist: idna (==3.11) ; python_version >= "3.9"
Requires-Dist: importlib-metadata (==8.7.0) ; python_version >= "3.9"
Requires-Dist: opentelemetry-api (==1.37.0) ; python_version >= "3.9"
Requires-Dist: opentelemetry-exporter-otlp (==1.37.0) ; python_version >= "3.9"
Requires-Dist: opentelemetry-exporter-otlp-proto-common (==1.37.0) ; python_version >= "3.9"
Requires-Dist: opentelemetry-exporter-otlp-proto-grpc (==1.37.0) ; python_version >= "3.9"
Requires-Dist: opentelemetry-exporter-otlp-proto-http (==1.37.0) ; python_version >= "3.9"
Requires-Dist: opentelemetry-proto (==1.37.0) ; python_version >= "3.9"
Requires-Dist: opentelemetry-sdk (==1.37.0) ; python_version >= "3.9"
Requires-Dist: opentelemetry-semantic-conventions (==0.58b0) ; python_version >= "3.9"
Requires-Dist: prometheus-client (==0.22.1) ; python_version >= "3.9"
Requires-Dist: protobuf (==6.33.1) ; python_version >= "3.9"
Requires-Dist: pydantic (==2.11.9) ; python_version >= "3.9"
Requires-Dist: pydantic-core (==2.33.2) ; python_version >= "3.9"
Requires-Dist: pydantic-settings (==2.10.1) ; python_version >= "3.9"
Requires-Dist: python-dotenv (==1.2.1) ; python_version >= "3.9"
Requires-Dist: requests (==2.32.5) ; python_version >= "3.9"
Requires-Dist: setuptools (==80.9.0) ; python_version >= "3.9"
Requires-Dist: typing-extensions (==4.15.0) ; python_version >= "3.9"
Requires-Dist: typing-inspection (==0.4.2) ; python_version >= "3.9"
Requires-Dist: urllib3 (==2.5.0) ; python_version >= "3.9"
Requires-Dist: zipp (==3.23.0) ; python_version >= "3.9"
